xy_string/__init__.py
xy_string/utils.py
xy_string-1.0.5.dist-info/LICENSE
xy_string-1.0.5.dist-info/METADATA
xy_string-1.0.5.dist-info/WHEEL
xy_string-1.0.5.dist-info/top_level.txt
xy_string-1.0.5.dist-info/RECORD
